aiogram_i18n/__init__.py
aiogram_i18n/__main__.py
aiogram_i18n/__meta__.py
aiogram_i18n/context.py
aiogram_i18n/exceptions.py
aiogram_i18n/middleware.py
aiogram_i18n/py.typed
aiogram_i18n/types.py
aiogram_i18n/cores/__init__.py
aiogram_i18n/cores/base.py
aiogram_i18n/cores/fluent_compile_core.py
aiogram_i18n/cores/fluent_runtime_core.py
aiogram_i18n/cores/gnu_text_core.py
aiogram_i18n/lazy/__init__.py
aiogram_i18n/lazy/factory.py
aiogram_i18n/lazy/proxy.py
aiogram_i18n/managers/__init__.py
aiogram_i18n/managers/base.py
aiogram_i18n/managers/const.py
aiogram_i18n/managers/fsm.py
aiogram_i18n/managers/memory.py
aiogram_i18n/managers/redis.py
aiogram_i18n/utils/__init__.py
aiogram_i18n/utils/attrdict.py
aiogram_i18n/utils/magic_proxy.py
aiogram_i18n/utils/stub_tree.py
aiogram_i18n/utils/text_decorator.py
aiogram_i18n/utils/cli/__init__.py
aiogram_i18n/utils/cli/base.py
aiogram_i18n/utils/cli/echo.py
aiogram_i18n/utils/cli/extract.py
aiogram_i18n/utils/cli/multiple_extract.py
aiogram_i18n/utils/cli/stub.py
aiogram_i18n/utils/fluent_extract/__init__.py
aiogram_i18n/utils/fluent_extract/base.py
aiogram_i18n/utils/fluent_extract/models.py
aiogram_i18n/utils/fluent_extract/parser.py
aiogram_i18n/utils/fluent_stub/__init__.py
aiogram_i18n/utils/fluent_stub/visitor.py
aiogram_i18n/utils/gnutext_stub/__init__.py
aiogram_i18n/utils/gnutext_stub/parser.py
aiogram_i18n-1.3.4.dist-info/METADATA
aiogram_i18n-1.3.4.dist-info/WHEEL
aiogram_i18n-1.3.4.dist-info/entry_points.txt
aiogram_i18n-1.3.4.dist-info/RECORD
