Metadata-Version: 2.1
Name: aiogram_i18n
Version: 1.3.4
Summary: small translation tools for aiogram
Project-URL: Repository, https://github.com/aiogram/aiogram_i18n
Author: RootShinobi
License: MIT License
Keywords: aiogram,api,asyncio,bot,fluent,framework,gnutext,i18n,telegram,wrapper
Classifier: License :: OSI Approved :: MIT License
Classifier: Operating System :: OS Independent
Classifier: Programming Language :: Python :: 3
Classifier: Programming Language :: Python :: 3.8
Classifier: Programming Language :: Python :: 3.9
Classifier: Programming Language :: Python :: 3.10
Classifier: Programming Language :: Python :: 3.11
Classifier: Typing :: Typed
Requires-Python: >=3.8
Requires-Dist: aiogram>=3.0.0b8
Requires-Dist: click~=8.1.0
Provides-Extra: compiler
Requires-Dist: fluent-compiler~=1.0; extra == 'compiler'
Provides-Extra: dev
Requires-Dist: black~=23.7.0; extra == 'dev'
Requires-Dist: mypy~=1.4.1; extra == 'dev'
Requires-Dist: packaging~=23.0; extra == 'dev'
Requires-Dist: pre-commit~=3.3.3; extra == 'dev'
Requires-Dist: ruff~=0.0.280; extra == 'dev'
Provides-Extra: runtime
Requires-Dist: fluent-runtime~=0.4.0; extra == 'runtime'
Provides-Extra: test
Requires-Dist: fluent-compiler~=1.0; extra == 'test'
Requires-Dist: fluent-runtime~=0.4.0; extra == 'test'
Requires-Dist: libcst~=1.0.1; extra == 'test'
Requires-Dist: pytest-asyncio~=0.21.1; extra == 'test'
Requires-Dist: pytest-cov~=4.0.0; extra == 'test'
Requires-Dist: pytest-lazy-fixture~=0.6.3; extra == 'test'
Requires-Dist: pytest~=7.4.0; extra == 'test'
